megashtein/__init__.py
megashtein/megashtein_trained_model.pth
megashtein/models.py
megashtein/training/__init__.py
megashtein/training/train.py
megashtein/training/train_model.py
megashtein-0.1.5.dist-info/METADATA
megashtein-0.1.5.dist-info/WHEEL
megashtein-0.1.5.dist-info/licenses/LICENSE
megashtein-0.1.5.dist-info/RECORD
