Metadata-Version: 2.4
Name: megashtein
Version: 0.1.5
Summary: Neural network-based string similarity using squared Euclidean approximation to Levenshtein distance
Project-URL: Homepage, https://github.com/Sawyer-Powell/megashtein
Project-URL: Repository, https://github.com/Sawyer-Powell/megashtein
Project-URL: Documentation, https://github.com/Sawyer-Powell/megashtein
Project-URL: Issues, https://github.com/Sawyer-Powell/megashtein
Author-email: Sawyer Powell <sawyerhpowell@gmail.com>
License: MIT
License-File: LICENSE
Keywords: fuzzy-search,levenshtein-distance,neural-network,pytorch,string-similarity
Classifier: Intended Audience :: Developers
Classifier: Intended Audience :: Science/Research
Classifier: License :: OSI Approved :: MIT License
Classifier: Programming Language :: Python :: 3
Classifier: Programming Language :: Python :: 3.13
Classifier: Topic :: Scientific/Engineering :: Artificial Intelligence
Classifier: Topic :: Software Development :: Libraries :: Python Modules
Classifier: Topic :: Text Processing
Requires-Python: >=3.13
Requires-Dist: torch>=2.6.0
